exojax/ExoJAX_version.py
exojax/__init__.py
exojax/atm/__init__.py
exojax/atm/amclouds.py
exojax/atm/atmconvert.py
exojax/atm/atmphys.py
exojax/atm/atmprof.py
exojax/atm/condensate.py
exojax/atm/idealgas.py
exojax/atm/lorentz_lorenz.py
exojax/atm/polarizability.py
exojax/atm/psat.py
exojax/atm/simple_clouds.py
exojax/atm/viscosity.py
exojax/atm/vterm.py
exojax/data/README.md
exojax/data/__init__.py
exojax/data/abundance/AAG2021.dat
exojax/data/abundance/xspec_abundance.txt
exojax/data/atom/HITRAN_molparam.txt
exojax/data/atom/NIST_Atomic_Ionization_Energies.txt
exojax/data/atom/atomic.txt
exojax/data/atom/barklem_collet_2016_pff.txt
exojax/data/atom/birklem_collet_2016_pff.txt
exojax/data/atom/iso_mn.txt
exojax/data/clouds/ammonia_liquid_density.csv
exojax/data/clouds/drag_force.txt
exojax/data/opacity/FeH_Hargreaves2010.csv
exojax/data/premodit/elower_grid_trange.npz
exojax/data/premodit/elower_grid_trange_v2.npz
exojax/data/testdata/20250503072507__1H2-16O__296.0K.csv
exojax/data/testdata/CO100percent_500K.feather
exojax/data/testdata/H2-H2_TEST.cia
exojax/data/testdata/filter_sdss_g.csv
exojax/data/testdata/jupiter_corrected.dat
exojax/data/testdata/lpf_rt_test_hitemp_ref.txt
exojax/data/testdata/lpf_rt_test_ref.txt
exojax/data/testdata/lpf_test_hitemp_ref.txt
exojax/data/testdata/lpf_test_ref.txt
exojax/data/testdata/luhman16a_spectra_detector1.csv
exojax/data/testdata/miegrid_lognorm_test.mg.npz
exojax/data/testdata/modit_rt_test_hitemp_ref.txt
exojax/data/testdata/modit_rt_test_ref.txt
exojax/data/testdata/modit_rt_test_vald_ref.txt
exojax/data/testdata/modit_test_hitemp_ref.txt
exojax/data/testdata/modit_test_hitemp_ref_air.txt
exojax/data/testdata/modit_test_ref.txt
exojax/data/testdata/moldb_vald.pickle
exojax/data/testdata/premodit_reflect_test_ref.txt
exojax/data/testdata/premodit_rt_test_hitemp_ref.txt
exojax/data/testdata/premodit_rt_test_ref.txt
exojax/data/testdata/premodit_test_hitemp_ref.txt
exojax/data/testdata/premodit_test_ref.txt
exojax-2.2.2.dist-info/licenses/LICENSE
exojax-2.2.2.dist-info/licenses/LICENSES_bundled.txt
exojax-2.2.2.dist-info/METADATA
exojax-2.2.2.dist-info/WHEEL
exojax-2.2.2.dist-info/top_level.txt
exojax-2.2.2.dist-info/RECORD
