Metadata-Version: 2.4
Name: ExoJAX
Version: 2.2.2
Summary: Differentiable exoplanet spectroscopy and atmospheric tools in JAX.
Author-email: Hajime Kawahara and ExoJAX developers <divrot@gmail.com>
Maintainer-email: Hajime Kawahara <divrot@gmail.com>
Project-URL: Homepage, https://secondearths.sakura.ne.jp/exojax/
Project-URL: Repository, https://github.com/HajimeKawahara/exojax
Project-URL: Documentation, https://secondearths.sakura.ne.jp/exojax/
Project-URL: Bug Tracker, https://github.com/HajimeKawahara/exojax/issues
Classifier: Programming Language :: Python
Classifier: Programming Language :: Python :: 3.9
Classifier: Programming Language :: Python :: 3.10
Classifier: Programming Language :: Python :: 3.11
Classifier: Operating System :: OS Independent
Requires-Python: >=3.9
License-File: LICENSE
License-File: LICENSES_bundled.txt
Requires-Dist: jax
Requires-Dist: jaxlib
Requires-Dist: hitran-api
Requires-Dist: beautifulsoup4
Requires-Dist: hjson
Requires-Dist: tqdm
Requires-Dist: PyMieScatt
Requires-Dist: radis>=0.15.2
Requires-Dist: numba
Requires-Dist: tables
Requires-Dist: pandas
Requires-Dist: termcolor
Requires-Dist: h5py
Requires-Dist: joblib
Requires-Dist: astroquery
Requires-Dist: psutil
Requires-Dist: json_tricks
Requires-Dist: habanero<=1.2.6
Requires-Dist: numpy<2
Dynamic: license-file
